dashai_plugin_hernan3/__init__.py
dashai_plugin_hernan3/dataloader_class_template.py
dashai_plugin_hernan3/metric_class_template.py
dashai_plugin_hernan3/model_class_template.py
dashai_plugin_hernan3/task_class_template.py
dashai_plugin_hernan3-1.0.dist-info/METADATA
dashai_plugin_hernan3-1.0.dist-info/WHEEL
dashai_plugin_hernan3-1.0.dist-info/entry_points.txt
dashai_plugin_hernan3-1.0.dist-info/RECORD
